LICENSE
MANIFEST.in
pyproject.toml
setup.py
ctpfrec/__init__.py
ctpfrec/cy.pxi
ctpfrec/cy_double.pxi
ctpfrec/cy_double_nonwindows.pyx
ctpfrec/cy_double_windows.pyx
ctpfrec/cy_float.pxi
ctpfrec/cy_float_nonwindows.pyx
ctpfrec/cy_float_windows.pyx
ctpfrec/return0.pyx
ctpfrec/return1.pyx
ctpfrec.egg-info/PKG-INFO
ctpfrec.egg-info/SOURCES.txt
ctpfrec.egg-info/dependency_links.txt
ctpfrec.egg-info/top_level.txt